azure/keyvault/administration/__init__.py
azure/keyvault/administration/_access_control_client.py
azure/keyvault/administration/_backup_client.py
azure/keyvault/administration/_enums.py
azure/keyvault/administration/_models.py
azure/keyvault/administration/_sdk_moniker.py
azure/keyvault/administration/_settings_client.py
azure/keyvault/administration/_version.py
azure/keyvault/administration/py.typed
azure/keyvault/administration/_generated/__init__.py
azure/keyvault/administration/_generated/_client.py
azure/keyvault/administration/_generated/_configuration.py
azure/keyvault/administration/_generated/_patch.py
azure/keyvault/administration/_generated/_validation.py
azure/keyvault/administration/_generated/_version.py
azure/keyvault/administration/_generated/py.typed
azure/keyvault/administration/_generated/_utils/__init__.py
azure/keyvault/administration/_generated/_utils/model_base.py
azure/keyvault/administration/_generated/_utils/serialization.py
azure/keyvault/administration/_generated/_utils/utils.py
azure/keyvault/administration/_generated/aio/__init__.py
azure/keyvault/administration/_generated/aio/_client.py
azure/keyvault/administration/_generated/aio/_configuration.py
azure/keyvault/administration/_generated/aio/_patch.py
azure/keyvault/administration/_generated/aio/operations/__init__.py
azure/keyvault/administration/_generated/aio/operations/_operations.py
azure/keyvault/administration/_generated/aio/operations/_patch.py
azure/keyvault/administration/_generated/models/__init__.py
azure/keyvault/administration/_generated/models/_enums.py
azure/keyvault/administration/_generated/models/_models.py
azure/keyvault/administration/_generated/models/_patch.py
azure/keyvault/administration/_generated/operations/__init__.py
azure/keyvault/administration/_generated/operations/_operations.py
azure/keyvault/administration/_generated/operations/_patch.py
azure/keyvault/administration/_internal/__init__.py
azure_keyvault_administration-4.6.0.dist-info/LICENSE
azure_keyvault_administration-4.6.0.dist-info/METADATA
azure_keyvault_administration-4.6.0.dist-info/WHEEL
azure_keyvault_administration-4.6.0.dist-info/top_level.txt
azure_keyvault_administration-4.6.0.dist-info/RECORD
